nonlindyn/__init__.py
nonlindyn/rk4.py
nonlindyn-0.1.dist-info/DESCRIPTION.rst
nonlindyn-0.1.dist-info/METADATA
nonlindyn-0.1.dist-info/RECORD
nonlindyn-0.1.dist-info/WHEEL
nonlindyn-0.1.dist-info/metadata.json
nonlindyn-0.1.dist-info/top_level.txt
