Metadata-Version: 2.0
Name: nonlindyn
Version: 0.1
Summary: Library to support analysing nonlinear dynamical systems
Home-page: http://github.com/andram/nonlindyn
Author: Andreas Amann
Author-email: a.amann@ucc.ie
License: GPL
Platform: UNKNOWN
